README.md
setup.cfg
setup.py
bvn/__init__.py
bvn/bvn_step.py
bvn/get_permutation.py
bvn.egg-info/PKG-INFO
bvn.egg-info/SOURCES.txt
bvn.egg-info/dependency_links.txt
bvn.egg-info/requires.txt
bvn.egg-info/top_level.txt